{
  "testnet": {
    "packageId": "0x5b0bb1e60ae43b411e2ed92c51c210fa674cd70ce162116a8bf9497c1f8be08a",
    "upgradeCap": "0xb1cfb61e7011cf07c7faaf7586866710688e4965b6126187269ca9200e7ccf7c",
    "publishDigest": "FGJ6eEXsP3NQeB3B8F9jrmECtuoKfpdpsnN8dNZCYpbE",
    "mockLenderAdminCap": "0x7a99de337f53e280948eeb1d1642221e0fd2918c4a4359cd7cf2a3e445f09418",
    "lendingPoolUsdc": "0xfaf55b512f8f73d4b40b053ecf0a0f882d15d1d16f2b2b0d3c16b9c641c492aa",
    "lendingPoolApyBps": 1000,
    "usdcType": "0xa1ec7fc00a6f40db9693ad1415d0c193ad3906494428cf252621037bd7117e29::usdc::USDC",
    "publishedModules": [
      "merchant_registry",
      "payment_receipt",
      "spending_vault",
      "lender_adapter",
      "mock_lender",
      "loyalty"
    ],
    "notes": "Republished 2026-06-02 with the security-hardened contracts: payment_receipt::pay is the only way to mint a Receipt/PaymentMade (moves the funds itself; authentic amount + Clock timestamp; soulbound receipt), loyalty::earn consumes a hot-potato PaymentProof (no forge/replay), spending_vault::withdraw clamps to redeemable, mock_lender bounds apy_bps + guards accrued. Lender keeps principal (1:1) separate from an admin-funded yield_reserve, so redeem never aborts. Fund the buffer via mock_lender::fund_yield (AdminCap-gated). Supersedes 0x2e7adfe1... (pre-hardening) and 0xc7073f8c... (commingled reserve)."
  }
}
